wikiscrape/__init__.py
wikiscrape/coordinates.py
wikiscrape/header.py
wikiscrape/infobox.py
wikiscrape/linked_text.py
wikiscrape/markdown.py
wikiscrape/wikiobject.py
wikiscrape/wikipage.py
wikiscrape/wikitable.py
wikiscrape-0.9.0.dist-info/METADATA
wikiscrape-0.9.0.dist-info/WHEEL
wikiscrape-0.9.0.dist-info/RECORD
